LICENSE.txt
MANIFEST.in
README.md
setup.py
aiophue/__init__.py
aiophue/bridge.py
aiophue/group.py
aiophue/light.py
aiophue/sensor.py
aiophue.egg-info/PKG-INFO
aiophue.egg-info/SOURCES.txt
aiophue.egg-info/dependency_links.txt
aiophue.egg-info/requires.txt
aiophue.egg-info/top_level.txt