Metadata-Version: 1.0
Name: aiophue
Version: 0.0.2
Summary: Control Philips Hue using AsyncIO
Home-page: https://github.com/NiekKeijzer/aiphue
Author: Niek Keijzer
Author-email: info@niekkeijzer.com
License: MIT
Platform: UNKNOWN
